{
  "timestamp": "2026-06-03T20:48:55.856174",
  "items": {
    "DGS10": {
      "name": "10Y 국채금리",
      "value": 4.46,
      "unit": "%",
      "status": 1,
      "threshold_bands": [
        4.0,
        4.6,
        5.0
      ],
      "direction": "up",
      "weight": 2
    },
    "T10Y2Y": {
      "name": "10Y-2Y 금리차",
      "value": 0.41,
      "unit": "%p",
      "status": 1,
      "threshold_bands": [
        -0.5,
        0,
        0.5
      ],
      "direction": "down",
      "weight": 2
    },
    "BAMLH0A0HYM2": {
      "name": "HY 스프레드",
      "value": 2.71,
      "unit": "%",
      "status": 0,
      "threshold_bands": [
        3.5,
        4.5,
        6.0
      ],
      "direction": "up",
      "weight": 3
    },
    "BAMLC0A0CM": {
      "name": "IG 스프레드",
      "value": 0.74,
      "unit": "%",
      "status": 0,
      "threshold_bands": [
        1.2,
        1.6,
        2.2
      ],
      "direction": "up",
      "weight": 2
    },
    "DFII10": {
      "name": "10Y 실질금리",
      "value": 2.07,
      "unit": "%",
      "status": 2,
      "threshold_bands": [
        1.5,
        2.0,
        2.5
      ],
      "direction": "up",
      "weight": 2
    },
    "T10YIE": {
      "name": "기대인플레",
      "value": 2.39,
      "unit": "%",
      "status": 1,
      "threshold_bands": [
        2.3,
        2.6,
        3.0
      ],
      "direction": "up",
      "weight": 2
    },
    "VIX": {
      "name": "VIX",
      "value": 16.059999465942383,
      "unit": "pt",
      "status": 1,
      "threshold_bands": [
        15,
        20,
        30
      ],
      "direction": "up",
      "weight": 2
    }
  },
  "composite": 27,
  "verdict": "주의"
}